nude.py
setup.cfg
setup.py
nonude.egg-info/PKG-INFO
nonude.egg-info/SOURCES.txt
nonude.egg-info/dependency_links.txt
nonude.egg-info/entry_points.txt
nonude.egg-info/not-zip-safe
nonude.egg-info/top_level.txt