Metadata-Version: 1.1
Name: nonude
Version: 1.1
Summary: Avoiding nude images in upload and its detection.
Home-page: https://github.com/gearsystems/nonude
Author: GEAR Systems
Author-email: info@gearsystems.com
License: UNKNOWN
Download-URL: https://github.com/gearsystems/nonude
Keywords: nude
Platform: Linux/Mac
Classifier: Programming Language :: Python
Classifier: Programming Language :: Python :: 2
Classifier: Programming Language :: Python :: 3
